ckanext/__init__.py
ckanext/federated_index/__init__.py
ckanext/federated_index/config.py
ckanext/federated_index/config_declaration.yaml
ckanext/federated_index/interfaces.py
ckanext/federated_index/plugin.py
ckanext/federated_index/shared.py
ckanext/federated_index/storage.py
ckanext/federated_index/types.py
ckanext/federated_index/assets/script.js
ckanext/federated_index/assets/style.css
ckanext/federated_index/assets/webassets.yml
ckanext/federated_index/logic/__init__.py
ckanext/federated_index/logic/action.py
ckanext/federated_index/logic/auth.py
ckanext/federated_index/logic/schema.py
ckanext/federated_index/logic/validators.py
ckanext/federated_index/migration/federated_index/alembic.ini
ckanext/federated_index/migration/federated_index/env.py
ckanext/federated_index/migration/federated_index/script.py.mako
ckanext/federated_index/migration/federated_index/versions/001_fce2130b4dc0_create_record_table.py
ckanext/federated_index/migration/federated_index/versions/002_66d40f567674_use_timezone.py
ckanext/federated_index/model/__init__.py
ckanext/federated_index/model/record.py
ckanext/federated_index/templates/snippets/package_item.html
ckanext/federated_index/tests/__init__.py
ckanext/federated_index/tests/conftest.py
ckanext/federated_index/tests/test_plugin.py
ckanext/federated_index/tests/test_storage.py
ckanext/federated_index/tests/logic/__init__.py
ckanext/federated_index/tests/logic/test_action.py
ckanext/federated_index/tests/logic/test_validators.py
ckanext_federated_index-0.1.1.post1.dist-info/LICENSE
ckanext_federated_index-0.1.1.post1.dist-info/METADATA
ckanext_federated_index-0.1.1.post1.dist-info/WHEEL
ckanext_federated_index-0.1.1.post1.dist-info/entry_points.txt
ckanext_federated_index-0.1.1.post1.dist-info/top_level.txt
ckanext_federated_index-0.1.1.post1.dist-info/RECORD
